escapeorangebox/__init__.py
escapeorangebox/__main__.py
escapeorangebox-0.0.3.dist-info/DESCRIPTION.rst
escapeorangebox-0.0.3.dist-info/METADATA
escapeorangebox-0.0.3.dist-info/RECORD
escapeorangebox-0.0.3.dist-info/WHEEL
escapeorangebox-0.0.3.dist-info/entry_points.txt
escapeorangebox-0.0.3.dist-info/metadata.json
escapeorangebox-0.0.3.dist-info/top_level.txt
