Metadata-Version: 2.0
Name: escapeorangebox
Version: 0.0.3
Summary: A command line utility for downloading metadata from Google Play Music
Home-page: https://github.com/erikbrinkman/escapeorangebox
Author: Erik Brinkman
Author-email: erik.brinkman@gmail.com
License: MIT
Platform: UNKNOWN
Requires-Dist: gmusicapi (~=10.1.2)
Provides-Extra: dev
Requires-Dist: autopep8 (~=1.3); extra == 'dev'
Requires-Dist: flake8 (~=3.4); extra == 'dev'
Requires-Dist: ipython (~=6.1); extra == 'dev'
Requires-Dist: setuptools (~=38.2); extra == 'dev'
Requires-Dist: twine (~=1.9); extra == 'dev'
Requires-Dist: wheel (~=0.29); extra == 'dev'
